ivtff/__init__.py
ivtff-0.0.1.dist-info/METADATA
ivtff-0.0.1.dist-info/WHEEL
ivtff-0.0.1.dist-info/licenses/LICENSE
ivtff-0.0.1.dist-info/RECORD
