Metadata-Version: 2.1
Name: ivtff
Version: 0.0.1
Summary: A library for working with IVTFF transliteration files
Project-URL: Homepage, https://github.com/jere-mie/ivtff-py
Project-URL: Bug Tracker, https://github.com/jere-mie/ivtff-py/issues
Author-email: Jeremie Bornais <jeremiedevelops@gmail.com>
License-File: LICENSE
Classifier: License :: OSI Approved :: MIT License
Classifier: Operating System :: OS Independent
Classifier: Programming Language :: Python :: 3
Requires-Python: >=3.6
